gcs_oauth2_boto_env_plugin.py
gcs_oauth2_boto_env_plugin-0.1.3.dist-info/DESCRIPTION.rst
gcs_oauth2_boto_env_plugin-0.1.3.dist-info/METADATA
gcs_oauth2_boto_env_plugin-0.1.3.dist-info/RECORD
gcs_oauth2_boto_env_plugin-0.1.3.dist-info/WHEEL
gcs_oauth2_boto_env_plugin-0.1.3.dist-info/metadata.json
gcs_oauth2_boto_env_plugin-0.1.3.dist-info/top_level.txt
