Metadata-Version: 2.0
Name: gcs-oauth2-boto-env-plugin
Version: 0.1.3
Summary: Google Storage auth2 plugin with support for passing service key via environment
Home-page: https://github.com/rs/gcs-oauth2-boto-env-plugin
Author: Olivier Poitrey
Author-email: rs@dailymotion.com
License: MIT
Keywords: oauth2 gcs s3 boto plugin docker
Platform: UNKNOWN
Classifier: Development Status :: 4 - Beta
Classifier: Intended Audience :: Developers
Classifier: License :: OSI Approved :: MIT License
Classifier: Natural Language :: English
Classifier: Operating System :: Unix
Classifier: Programming Language :: Python :: 2.7
Classifier: Programming Language :: Python :: 3.4
Classifier: Programming Language :: Python :: Implementation :: PyPy
Classifier: Operating System :: OS Independent
Requires-Dist: gcs-oauth2-boto-plugin (==1.9)
